pptestmariuszowczarek/__init__.py
pptestmariuszowczarek/m_mod_pptest.py
pptestmariuszowczarek-0.0.4.dist-info/LICENCE.txt
pptestmariuszowczarek-0.0.4.dist-info/METADATA
pptestmariuszowczarek-0.0.4.dist-info/WHEEL
pptestmariuszowczarek-0.0.4.dist-info/top_level.txt
pptestmariuszowczarek-0.0.4.dist-info/RECORD
