Metadata-Version: 2.1
Name: pptestmariuszowczarek
Version: 0.0.4
Summary: my test package
Author-email: Mariusz Owczarek <abc@wp.pl>
License: MIT License
Keywords: pptestmariuszowczarek,funny functions,name, surname
Classifier: Framework :: IDLE
Requires-Python: >=3.0
License-File: LICENCE.txt
Requires-Dist: numpy ; python_version >= "3.0"
